MANIFEST.in
README.rst
setup.py
devilry/__init__.py
devilry/version.json
devilry.egg-info/PKG-INFO
devilry.egg-info/SOURCES.txt
devilry.egg-info/dependency_links.txt
devilry.egg-info/not-zip-safe
devilry.egg-info/requires.txt
devilry.egg-info/top_level.txt
devilry/apps/__init__.py
devilry/apps/core/__init__.py
devilry/apps/core/admin.py
devilry/apps/core/apps.py
devilry/apps/core/deliverystore.py
devilry/apps/core/devilry_core_mommy_factories.py
devilry/apps/core/group_user_lookup.py
devilry/apps/core/mommy_recipes.py
devilry/apps/core/testhelper.py
devilry/apps/core/testhelpers.py
devilry/apps/core/urls.py
devilry/apps/core/migrations/0001_initial.py
devilry/apps/core/migrations/0002_auto_20150915_1127.py
devilry/apps/core/migrations/0003_auto_20150917_1537.py
devilry/apps/core/migrations/0004_examiner_relatedexaminer.py
devilry/apps/core/migrations/0005_relatedexaminer_automatic_anonymous_id.py
devilry/apps/core/migrations/0006_auto_20151112_1851.py
devilry/apps/core/migrations/0007_assignment_gradeform_setup_json.py
devilry/apps/core/migrations/0008_auto_20151222_1955.py
devilry/apps/core/migrations/0009_assignmentgroup_batchoperation.py
devilry/apps/core/migrations/0010_assignment_anonymizationmode.py
devilry/apps/core/migrations/0011_datamigrate_anonymous_to_anonymizationmode.py
devilry/apps/core/migrations/0012_auto_20160111_2019.py
devilry/apps/core/migrations/0013_auto_20160111_2021.py
devilry/apps/core/migrations/0014_auto_20160112_1052.py
devilry/apps/core/migrations/0015_assignment_uses_custom_candidate_ids.py
devilry/apps/core/migrations/0016_auto_20160112_1831.py
devilry/apps/core/migrations/0017_candidate_relatedstudent_replaces_student_field.py
devilry/apps/core/migrations/0018_auto_20160112_1923.py
devilry/apps/core/migrations/0019_auto_20160113_2037.py
devilry/apps/core/migrations/0020_relatedexaminer_active.py
devilry/apps/core/migrations/0021_examiner_relatedexaminer_replaces_user_field.py
devilry/apps/core/migrations/0022_auto_20160114_1520.py
devilry/apps/core/migrations/0023_auto_20160114_1522.py
devilry/apps/core/migrations/0024_auto_20160114_1524.py
devilry/apps/core/migrations/0025_auto_20160114_1525.py
