Metadata-Version: 1.0
Name: devilry
Version: 3.4.1
Summary: A system for handling electronic deliveries. See https://github.com/devilry/devilry-django.
Home-page: http://devilry.org
Author: Tor Johansen, Espen Angell Kristiansen, Bendik Opstad, Vegard Angell, Magne Westlie, Ilya Kostolomov, Christian Tryti, Rebekka Mørken, Stian Julseth
Author-email: devilry-contact@googlegroups.com
License: BSD
Platform: UNKNOWN
